jiminy_py/__init__.py
jiminy_py/__init__.pyi
jiminy_py/dynamics.py
jiminy_py/dynamics.pyi
jiminy_py/log.py
jiminy_py/log.pyi
jiminy_py/plot.py
jiminy_py/plot.pyi
jiminy_py/py.typed
jiminy_py/robot.py
jiminy_py/robot.pyi
jiminy_py/simulator.py
jiminy_py/simulator.pyi
jiminy_py/tree.py
jiminy_py/tree.pyi
jiminy_py/.dylibs/libboost_container.dylib
jiminy_py/.dylibs/libboost_graph.dylib
jiminy_py/.dylibs/libboost_numpy310.dylib
jiminy_py/.dylibs/libboost_python310.dylib
jiminy_py/.dylibs/libeigenpy.dylib
jiminy_py/.dylibs/libhpp-fcl.dylib
jiminy_py/.dylibs/libpinocchio.2.7.0.dylib
jiminy_py/core/__init__.py
jiminy_py/core/__init__.pyi
jiminy_py/core/core.cpython-310-darwin.so
jiminy_py/core/core.pyi
jiminy_py/core/cmake/FindSphinx.cmake
jiminy_py/core/cmake/Findcppad.cmake
jiminy_py/core/cmake/Findcppadcg.cmake
jiminy_py/core/cmake/jiminyConfig.cmake
jiminy_py/core/cmake/jiminyConfigVersion.cmake
jiminy_py/core/eigenpy/__init__.py
jiminy_py/core/eigenpy/__init__.pyi
jiminy_py/core/eigenpy/eigenpy_pywrap.cpython-310-darwin.so
jiminy_py/core/eigenpy/eigenpy_pywrap.pyi
jiminy_py/core/eigenpy/windows_dll_manager.py
jiminy_py/core/eigenpy/windows_dll_manager.pyi
jiminy_py/core/hppfcl/__init__.py
jiminy_py/core/hppfcl/__init__.pyi
jiminy_py/core/hppfcl/hppfcl.cpython-310-darwin.so
jiminy_py/core/hppfcl/hppfcl.pyi
jiminy_py/core/hppfcl/viewer.py
jiminy_py/core/hppfcl/viewer.pyi
jiminy_py/core/include/jiminy/core/constants.h
jiminy_py/core/include/jiminy/core/fwd.h
jiminy_py/core/include/jiminy/core/macros.h
jiminy_py/core/include/jiminy/core/traits.h
jiminy_py/core/include/jiminy/core/constraints/abstract_constraint.h
jiminy_py/core/include/jiminy/core/constraints/distance_constraint.h
jiminy_py/core/include/jiminy/core/constraints/frame_constraint.h
jiminy_py/core/include/jiminy/core/constraints/joint_constraint.h
jiminy_py/core/include/jiminy/core/constraints/sphere_constraint.h
jiminy_py/core/include/jiminy/core/constraints/wheel_constraint.h
jiminy_py-1.8.13.dist-info/METADATA
jiminy_py-1.8.13.dist-info/WHEEL
jiminy_py-1.8.13.dist-info/entry_points.txt
jiminy_py-1.8.13.dist-info/top_level.txt
jiminy_py-1.8.13.dist-info/RECORD
