Metadata-Version: 2.1
Name: jiminy-py
Version: 1.8.13
Summary: Fast and light weight simulator of rigid poly-articulated systems.
Home-page: https://duburcqa.github.io/jiminy/README.html
Download-URL: https://github.com/duburcqa/jiminy/archive/1.8.13.tar.gz
Author: Alexis Duburcq
Author-email: alexis.duburcq@gmail.com
Maintainer: Alexis Duburcq
License: MIT
Project-URL: Documentation, https://duburcqa.github.io/jiminy
Project-URL: Bug Tracker, https://github.com/duburcqa/jiminy/issues
Project-URL: Source, https://github.com/duburcqa/jiminy
Keywords: robotics physics simulator
Classifier: Development Status :: 4 - Beta
Classifier: Intended Audience :: Science/Research
Classifier: Topic :: Scientific/Engineering :: Physics
Classifier: Topic :: Software Development :: Libraries :: Python Modules
Classifier: License :: OSI Approved :: MIT License
Classifier: Programming Language :: Python :: 3.10
Classifier: Programming Language :: Python :: 3.11
Classifier: Programming Language :: Python :: 3.12
Classifier: Programming Language :: Python :: 3.13
Requires-Python: >=3.10,<3.14
Requires-Dist: numpy<2.3,>=1.19
Requires-Dist: tomlkit
Requires-Dist: panda3d>=1.10.13
Requires-Dist: panda3d-simplepbr==0.11.2
Requires-Dist: panda3d-viewer
Requires-Dist: av>=8.0.0
Requires-Dist: trimesh
Requires-Dist: tqdm
Provides-Extra: dev
Requires-Dist: pybind11-stubgen<1.0; extra == "dev"
Requires-Dist: pillow; extra == "dev"
Requires-Dist: scipy; extra == "dev"
Requires-Dist: types-psutil>=5.9.5.20240511; extra == "dev"
Requires-Dist: types-Pillow; extra == "dev"
Requires-Dist: types-tqdm; extra == "dev"
Requires-Dist: flake8; extra == "dev"
Requires-Dist: pylint>=3.1; extra == "dev"
Requires-Dist: mypy>=1.5.0; extra == "dev"
Requires-Dist: pygments; extra == "dev"
Requires-Dist: colorama; extra == "dev"
Requires-Dist: sphinx>=4.0.0; extra == "dev"
Requires-Dist: sphinx-rtd-theme; extra == "dev"
Requires-Dist: myst-parser; extra == "dev"
Requires-Dist: nbsphinx!=0.8.8; extra == "dev"
Requires-Dist: aafigure; extra == "dev"
Requires-Dist: breathe; extra == "dev"
Requires-Dist: auditwheel>=5.2.1; extra == "dev"
Requires-Dist: build; extra == "dev"
Requires-Dist: patchelf>=0.14; sys_platform == "linux" and extra == "dev"
Provides-Extra: meshcat
Requires-Dist: meshcat>=0.3.2; extra == "meshcat"
Requires-Dist: psutil>=6.0; extra == "meshcat"
Requires-Dist: ipykernel<7.0,>=5.0; extra == "meshcat"
Requires-Dist: pillow; extra == "meshcat"
Requires-Dist: playwright>=1.43; extra == "meshcat"
Provides-Extra: plot
Requires-Dist: matplotlib>=3.7.0; extra == "plot"
